hebrew_numbers/__init__.py
hebrew_numbers/_version.py
hebrew_numbers/_version.pyi
hebrew_numbers/hebrew_numbers.py
hebrew_numbers/jinja.py
hebrew_numbers/py.typed
hebrew_numbers-0.2.1.dist-info/METADATA
hebrew_numbers-0.2.1.dist-info/WHEEL
hebrew_numbers-0.2.1.dist-info/RECORD
