Metadata-Version: 2.4
Name: hebrew-numbers
Version: 0.2.1
Summary: Convert numbers to Hebrew.
Project-URL: Source, https://github.com/tsvikas/hebrew-numbers
Project-URL: Changelog, https://github.com/tsvikas/hebrew-numbers/blob/main/CHANGELOG.md
Project-URL: Issues, https://github.com/tsvikas/hebrew-numbers/issues
Author-email: Tsvika Shapira <tsvikas@gmail.com>
License-Expression: MIT
Keywords: conversion,grammar,hebrew,i18n,jinja2,language,linguistics,localization,nlp,numbers
Classifier: Development Status :: 4 - Beta
Classifier: Natural Language :: Hebrew
Classifier: Operating System :: OS Independent
Classifier: Programming Language :: Python
Classifier: Programming Language :: Python :: 3
Classifier: Programming Language :: Python :: 3 :: Only
Classifier: Programming Language :: Python :: 3.10
Classifier: Programming Language :: Python :: 3.11
Classifier: Programming Language :: Python :: 3.12
Classifier: Programming Language :: Python :: 3.13
Classifier: Programming Language :: Python :: 3.14
Classifier: Topic :: Education
Classifier: Topic :: Office/Business
Classifier: Topic :: Software Development :: Libraries
Classifier: Typing :: Typed
Requires-Python: >=3.10
Requires-Dist: typing-extensions>=4.5.0; python_version < '3.12'
Provides-Extra: jinja
Requires-Dist: jinja2>=3.0.0; extra == 'jinja'
